odoo10_addon_l10n_es_partner-10.0.1.1.0-py2.7-nspkg.pth
odoo/addons/l10n_es_partner/README.rst
odoo/addons/l10n_es_partner/__init__.py
odoo/addons/l10n_es_partner/__manifest__.py
odoo/addons/l10n_es_partner/data/l10n_es_partner_data.xml
odoo/addons/l10n_es_partner/gen_src/README.rst
odoo/addons/l10n_es_partner/gen_src/__init__.py
odoo/addons/l10n_es_partner/gen_src/bics.xls
odoo/addons/l10n_es_partner/gen_src/gen_data_banks.py
odoo/addons/l10n_es_partner/i18n/bg.po
odoo/addons/l10n_es_partner/i18n/ca.po
odoo/addons/l10n_es_partner/i18n/cs.po
odoo/addons/l10n_es_partner/i18n/de.po
odoo/addons/l10n_es_partner/i18n/es.po
odoo/addons/l10n_es_partner/i18n/es_CO.po
odoo/addons/l10n_es_partner/i18n/es_CR.po
odoo/addons/l10n_es_partner/i18n/es_ES.po
odoo/addons/l10n_es_partner/i18n/eu.po
odoo/addons/l10n_es_partner/i18n/fr.po
odoo/addons/l10n_es_partner/i18n/gl.po
odoo/addons/l10n_es_partner/i18n/hr.po
odoo/addons/l10n_es_partner/i18n/l10n_es_partner.pot
odoo/addons/l10n_es_partner/i18n/nl.po
odoo/addons/l10n_es_partner/i18n/pl.po
odoo/addons/l10n_es_partner/i18n/pt.po
odoo/addons/l10n_es_partner/i18n/pt_BR.po
odoo/addons/l10n_es_partner/i18n/ru.po
odoo/addons/l10n_es_partner/i18n/sl.po
odoo/addons/l10n_es_partner/i18n/sv.po
odoo/addons/l10n_es_partner/i18n/tr.po
odoo/addons/l10n_es_partner/i18n/vi.po
odoo/addons/l10n_es_partner/models/__init__.py
odoo/addons/l10n_es_partner/models/account_journal.py
odoo/addons/l10n_es_partner/models/res_bank.py
odoo/addons/l10n_es_partner/models/res_partner.py
odoo/addons/l10n_es_partner/models/res_partner_bank.py
odoo/addons/l10n_es_partner/static/description/bank.svg
odoo/addons/l10n_es_partner/static/description/icon.png
odoo/addons/l10n_es_partner/tests/__init__.py
odoo/addons/l10n_es_partner/tests/test_l10n_es_partner.py
odoo/addons/l10n_es_partner/views/account_journal_view.xml
odoo/addons/l10n_es_partner/views/res_bank_view.xml
odoo/addons/l10n_es_partner/views/res_partner_bank_view.xml
odoo10_addon_l10n_es_partner-10.0.1.1.0.dist-info/METADATA
odoo10_addon_l10n_es_partner-10.0.1.1.0.dist-info/RECORD
odoo10_addon_l10n_es_partner-10.0.1.1.0.dist-info/WHEEL
odoo10_addon_l10n_es_partner-10.0.1.1.0.dist-info/namespace_packages.txt
odoo10_addon_l10n_es_partner-10.0.1.1.0.dist-info/top_level.txt
