Metadata-Version: 2.1
Name: odoo10-addon-l10n-es-partner
Version: 10.0.1.1.0
Summary: Adaptación de los clientes, proveedores y bancos para España
Home-page: https://github.com/OCA/l10n-spain
Author: ZikZak,Acysos,Tecnativa,Odoo Community Association (OCA)
Author-email: support@odoo-community.org
License: AGPL-3
Platform: UNKNOWN
Classifier: Programming Language :: Python
Classifier: Framework :: Odoo
Classifier: License :: OSI Approved :: GNU Affero General Public License v3
Requires-Python: ~=2.7
Requires-Dist: odoo10-addon-l10n-es-toponyms
Requires-Dist: odoo (<10.1dev,>=10.0)
Requires-Dist: requests
